{"textures":{"0":"modelengine:entity/dekubaba"},"elements":[{"from":[4.285714,5.8737497,7.140057],"to":[11.714286,5.8737497,11.140057],"rotation":{"angle":0.0,"axis":"y","origin":[8.0,5.8737497,9.140057]},"faces":{"east":{"uv":[0.0,0.0,1.75,0.0],"rotation":0,"texture":"#0","tintindex":0},"south":{"uv":[0.0,0.0,3.25,0.0],"rotation":0,"texture":"#0","tintindex":0},"north":{"uv":[0.0,0.0,3.25,0.0],"rotation":0,"texture":"#0","tintindex":0},"west":{"uv":[0.0,0.0,1.75,0.0],"rotation":0,"texture":"#0","tintindex":0},"up":{"uv":[7.25,5.75,4.0,4.0],"rotation":0,"texture":"#0","tintindex":0},"down":{"uv":[7.25,4.0,4.0,5.75],"rotation":0,"texture":"#0","tintindex":0}}},{"from":[4.285714,4.459704,10.553866],"to":[11.714286,4.459704,15.125296],"rotation":{"angle":45.0,"axis":"x","origin":[8.0,4.459704,12.553867]},"faces":{"east":{"uv":[0.0,0.0,2.0,0.0],"rotation":0,"texture":"#0","tintindex":0},"south":{"uv":[0.0,0.0,3.25,0.0],"rotation":0,"texture":"#0","tintindex":0},"north":{"uv":[0.0,0.0,3.25,0.0],"rotation":0,"texture":"#0","tintindex":0},"west":{"uv":[0.0,0.0,2.0,0.0],"rotation":0,"texture":"#0","tintindex":0},"up":{"uv":[7.25,2.0,4.0,0.0],"rotation":0,"texture":"#0","tintindex":0},"down":{"uv":[7.25,0.0,4.0,2.0],"rotation":0,"texture":"#0","tintindex":0}}}],"display":{"head":{"translation":[0.0,-6.4,0.0],"scale":[4.0,4.0,4.0]}}}