{"textures":{"11":"modelengine:entity/fox8"},"elements":[{"from":[6.285714,6.857143,6.0],"to":[9.714286,6.857143,11.142858],"rotation":{"angle":0.0,"axis":"y","origin":[8.571428,2.5714283,2.5714283]},"faces":{"east":{"uv":[8.5,6.0,10.75,6.0],"rotation":0,"texture":"#11","tintindex":0},"south":{"uv":[14.5,6.0,16.0,6.0],"rotation":0,"texture":"#11","tintindex":0},"north":{"uv":[10.75,6.0,12.25,6.0],"rotation":0,"texture":"#11","tintindex":0},"west":{"uv":[12.25,6.0,14.5,6.0],"rotation":0,"texture":"#11","tintindex":0},"up":{"uv":[12.25,6.0,10.75,3.75],"rotation":0,"texture":"#11","tintindex":0},"down":{"uv":[13.75,3.75,12.25,6.0],"rotation":0,"texture":"#11","tintindex":0}}},{"from":[2.8571424,8.0,6.0],"to":[6.285714,8.0,11.142858],"rotation":{"angle":0.0,"axis":"y","origin":[8.571428,2.5714283,2.5714283]},"faces":{"east":{"uv":[8.5,6.0,10.75,6.0],"rotation":0,"texture":"#11","tintindex":0},"south":{"uv":[14.5,6.0,16.0,6.0],"rotation":0,"texture":"#11","tintindex":0},"north":{"uv":[10.75,6.0,12.25,6.0],"rotation":0,"texture":"#11","tintindex":0},"west":{"uv":[12.25,6.0,14.5,6.0],"rotation":0,"texture":"#11","tintindex":0},"up":{"uv":[12.25,6.0,10.75,3.75],"rotation":0,"texture":"#11","tintindex":0},"down":{"uv":[13.75,3.75,12.25,6.0],"rotation":0,"texture":"#11","tintindex":0}}}],"display":{"head":{"translation":[0.0,-6.4,0.0],"scale":[4.0,4.0,4.0]}}}